zope.filerepresentation-6.0-py3.9-nspkg.pth
zope/filerepresentation/__init__.py
zope/filerepresentation/interfaces.py
zope/filerepresentation/tests.py
zope.filerepresentation-6.0.dist-info/LICENSE.txt
zope.filerepresentation-6.0.dist-info/METADATA
zope.filerepresentation-6.0.dist-info/WHEEL
zope.filerepresentation-6.0.dist-info/namespace_packages.txt
zope.filerepresentation-6.0.dist-info/top_level.txt
zope.filerepresentation-6.0.dist-info/zip-safe
zope.filerepresentation-6.0.dist-info/RECORD
